odoo/addons/delivery_carrier_warehouse/README.rst
odoo/addons/delivery_carrier_warehouse/__init__.py
odoo/addons/delivery_carrier_warehouse/__manifest__.py
odoo/addons/delivery_carrier_warehouse/i18n/ca.po
odoo/addons/delivery_carrier_warehouse/i18n/delivery_carrier_warehouse.pot
odoo/addons/delivery_carrier_warehouse/i18n/es_AR.po
odoo/addons/delivery_carrier_warehouse/i18n/it.po
odoo/addons/delivery_carrier_warehouse/models/__init__.py
odoo/addons/delivery_carrier_warehouse/models/sale_order.py
odoo/addons/delivery_carrier_warehouse/models/stock_warehouse.py
odoo/addons/delivery_carrier_warehouse/readme/CONTRIBUTORS.rst
odoo/addons/delivery_carrier_warehouse/readme/DESCRIPTION.rst
odoo/addons/delivery_carrier_warehouse/static/description/icon.png
odoo/addons/delivery_carrier_warehouse/static/description/index.html
odoo/addons/delivery_carrier_warehouse/tests/__init__.py
odoo/addons/delivery_carrier_warehouse/tests/test_delivery_carrier_warehouse.py
odoo/addons/delivery_carrier_warehouse/views/stock_warehouse.xml
odoo13_addon_delivery_carrier_warehouse-13.0.1.2.1.dev10.dist-info/METADATA
odoo13_addon_delivery_carrier_warehouse-13.0.1.2.1.dev10.dist-info/WHEEL
odoo13_addon_delivery_carrier_warehouse-13.0.1.2.1.dev10.dist-info/top_level.txt
odoo13_addon_delivery_carrier_warehouse-13.0.1.2.1.dev10.dist-info/RECORD
